bosa_connectors.cpython-311-x86_64-linux-gnu.so
bosa_connectors.pyi
bosa_connectors/__init__.pyi
bosa_connectors/action.pyi
bosa_connectors/action_response.pyi
bosa_connectors/connector.pyi
bosa_connectors/module.pyi
bosa_connectors/tool.pyi
bosa_connectors/auth/__init__.pyi
bosa_connectors/auth/api_key.pyi
bosa_connectors/auth/base.pyi
bosa_connectors/helpers/__init__.pyi
bosa_connectors/helpers/authenticator.pyi
bosa_connectors/helpers/integrations.pyi
bosa_connectors/helpers/tool_builder/__init__.pyi
bosa_connectors/helpers/tool_builder/base.pyi
bosa_connectors/helpers/tool_builder/gllm.pyi
bosa_connectors/helpers/tool_builder/json_schema_generator.pyi
bosa_connectors/helpers/tool_builder/langchain.pyi
bosa_connectors/models/__init__.pyi
bosa_connectors/models/action.pyi
bosa_connectors/models/file.pyi
bosa_connectors/models/result.pyi
bosa_connectors/models/token.pyi
bosa_connectors/models/user.pyi
bosa_connectors.build/.gitignore
bosa_connectors_binary-0.3.3.dist-info/METADATA
bosa_connectors_binary-0.3.3.dist-info/WHEEL
bosa_connectors_binary-0.3.3.dist-info/top_level.txt
bosa_connectors_binary-0.3.3.dist-info/RECORD
